COPYING.LESSER
setup.py
math2d/__init__.py
math2d/orientation.py
math2d/test.py
math2d/transform.py
math2d/vector.py
math2d.egg-info/PKG-INFO
math2d.egg-info/SOURCES.txt
math2d.egg-info/dependency_links.txt
math2d.egg-info/requires.txt
math2d.egg-info/top_level.txt
math2d/geometry/__init__.py
math2d/geometry/patch.py
test/test_line_segment.py